fft8_test/fft8.v
module fft8(
    input clk,
    input rst,
    input start,
    input signed [15:0] x0_real, x1_real, x2_real, x3_real, x4_real, x5_real, x6_real, x7_real,
    input signed [15:0] x0_imag, x1_imag, x2_imag, x3_imag, x4_imag, x5_imag, x6_imag, x7_imag,
    output reg signed [31:0] X0_real, X1_real, X2_real, X3_real, X4_real, X5_real, X6_real, X7_real,
    output reg signed [31:0] X0_imag, X1_imag, X2_imag, X3_imag, X4_imag, X5_imag, X6_imag, X7_imag,
    output reg valid
);

    // Fixed-point representation: 16.16 format for intermediate calculations
    // Twiddle factor constants (Q15 format: 1.15)
    localparam signed [15:0] TW_1_REAL =  16'h5A82;  // cos(π/4) ≈ 0.707
    localparam signed [15:0] TW_1_IMAG = -16'h5A82;  // -sin(π/4) ≈ -0.707
    localparam signed [15:0] TW_2_REAL =  16'h0000;  // cos(π/2) = 0
    localparam signed [15:0] TW_2_IMAG = -16'h8000;  // -sin(π/2) = -1
    localparam signed [15:0] TW_3_REAL = -16'h5A82;  // cos(3π/4) ≈ -0.707
    localparam signed [15:0] TW_3_IMAG = -16'h5A82;  // -sin(3π/4) ≈ -0.707

    // Stage registers for pipeline
    reg signed [31:0] stage1_real [0:7];
    reg signed [31:0] stage1_imag [0:7];
    reg signed [31:0] stage2_real [0:7];
    reg signed [31:0] stage2_imag [0:7];
    reg signed [31:0] stage3_real [0:7];
    reg signed [31:0] stage3_imag [0:7];
    
    // Pipeline control
    reg [2:0] pipeline_stage;
    reg processing;

    // Complex multiplier outputs
    wire signed [31:0] mult_out_real [0:3];
    wire signed [31:0] mult_out_imag [0:3];
    
    // Instantiate complex multipliers for twiddle factor multiplication
    complex_mult cmult0(
        .clk(clk),
        .a_real(stage2_real[1]),
        .a_imag(stage2_imag[1]),
        .b_real({TW_1_REAL, 16'b0}),
        .b_imag({TW_1_IMAG, 16'b0}),
        .result_real(mult_out_real[0]),
        .result_imag(mult_out_imag[0])
    );
    
    complex_mult cmult1(
        .clk(clk),
        .a_real(stage2_real[3]),
        .a_imag(stage2_imag[3]),
        .b_real({TW_2_REAL, 16'b0}),
        .b_imag({TW_2_IMAG, 16'b0}),
        .result_real(mult_out_real[1]),
        .result_imag(mult_out_imag[1])
    );
    
    complex_mult cmult2(
        .clk(clk),
        .a_real(stage2_real[5]),
        .a_imag(stage2_imag[5]),
        .b_real({TW_1_REAL, 16'b0}),
        .b_imag({TW_1_IMAG, 16'b0}),
        .result_real(mult_out_real[2]),
        .result_imag(mult_out_imag[2])
    );
    
    complex_mult cmult3(
        .clk(clk),
        .a_real(stage2_real[7]),
        .a_imag(stage2_imag[7]),
        .b_real({TW_3_REAL, 16'b0}),
        .b_imag({TW_3_IMAG, 16'b0}),
        .result_real(mult_out_real[3]),
        .result_imag(mult_out_imag[3])
    );

    always @(posedge clk or posedge rst) begin
        if (rst) begin
            pipeline_stage <= 0;
            processing <= 0;
            valid <= 0;
            // Reset all output registers
            X0_real <= 0; X1_real <= 0; X2_real <= 0; X3_real <= 0;
            X4_real <= 0; X5_real <= 0; X6_real <= 0; X7_real <= 0;
            X0_imag <= 0; X1_imag <= 0; X2_imag <= 0; X3_imag <= 0;
            X4_imag <= 0; X5_imag <= 0; X6_imag <= 0; X7_imag <= 0;
        end else begin
            case (pipeline_stage)
                3'd0: begin
                    valid <= 0;
                    if (start && !processing) begin
                        processing <= 1;
                        pipeline_stage <= 1;
                        // Stage 1: Radix-2 butterflies (no twiddle factors)
                        stage1_real[0] <= {x0_real, 16'b0} + {x4_real, 16'b0};
                        stage1_imag[0] <= {x0_imag, 16'b0} + {x4_imag, 16'b0};
                        stage1_real[1] <= {x1_real, 16'b0} + {x5_real, 16'b0};
                        stage1_imag[1] <= {x1_imag, 16'b0} + {x5_imag, 16'b0};
                        stage1_real[2] <= {x2_real, 16'b0} + {x6_real, 16'b0};
                        stage1_imag[2] <= {x2_imag, 16'b0} + {x6_imag, 16'b0};
                        stage1_real[3] <= {x3_real, 16'b0} + {x7_real, 16'b0};
                        stage1_imag[3] <= {x3_imag, 16'b0} + {x7_imag, 16'b0};
                        stage1_real[4] <= {x0_real, 16'b0} - {x4_real, 16'b0};
                        stage1_imag[4] <= {x0_imag, 16'b0} - {x4_imag, 16'b0};
                        stage1_real[5] <= {x1_real, 16'b0} - {x5_real, 16'b0};
                        stage1_imag[5] <= {x1_imag, 16'b0} - {x5_imag, 16'b0};
                        stage1_real[6] <= {x2_real, 16'b0} - {x6_real, 16'b0};
                        stage1_imag[6] <= {x2_imag, 16'b0} - {x6_imag, 16'b0};
                        stage1_real[7] <= {x3_real, 16'b0} - {x7_real, 16'b0};
                        stage1_imag[7] <= {x3_imag, 16'b0} - {x7_imag, 16'b0};
                    end
                end
                
                3'd1: begin
                    pipeline_stage <= 2;
                    // Stage 2: Second set of butterflies (no twiddle factors yet)
                    stage2_real[0] <= stage1_real[0] + stage1_real[2];
                    stage2_imag[0] <= stage1_imag[0] + stage1_imag[2];
                    stage2_real[1] <= stage1_real[1] + stage1_real[3];
                    stage2_imag[1] <= stage1_imag[1] + stage1_imag[3];
                    stage2_real[2] <= stage1_real[0] - stage1_real[2];
                    stage2_imag[2] <= stage1_imag[0] - stage1_imag[2];
                    stage2_real[3] <= stage1_real[1] - stage1_real[3];
                    stage2_imag[3] <= stage1_imag[1] - stage1_imag[3];
                    stage2_real[4] <= stage1_real[4] + stage1_real[6];
                    stage2_imag[4] <= stage1_imag[4] + stage1_imag[6];
                    stage2_real[5] <= stage1_real[5] + stage1_real[7];
                    stage2_imag[5] <= stage1_imag[5] + stage1_imag[7];
                    stage2_real[6] <= stage1_real[4] - stage1_real[6];
                    stage2_imag[6] <= stage1_imag[4] - stage1_imag[6];
                    stage2_real[7] <= stage1_real[5] - stage1_real[7];
                    stage2_imag[7] <= stage1_imag[5] - stage1_imag[7];
                end
                
                3'd2: begin
                    pipeline_stage <= 3;
                    // Wait for complex multipliers (twiddle factor multiplication)
                end
                
                3'd3: begin
                    pipeline_stage <= 4;
                    // Stage 3: Final butterflies with twiddle factor results
                    stage3_real[0] <= stage2_real[0] + stage2_real[1];
                    stage3_imag[0] <= stage2_imag[0] + stage2_imag[1];
                    stage3_real[1] <= stage2_real[4] + mult_out_real[0];
                    stage3_imag[1] <= stage2_imag[4] + mult_out_imag[0];
                    stage3_real[2] <= stage2_real[2] + mult_out_real[1];
                    stage3_imag[2] <= stage2_imag[2] + mult_out_imag[1];
                    stage3_real[3] <= stage2_real[6] + mult_out_real[2];
                    stage3_imag[3] <= stage2_imag[6] + mult_out_imag[2];
                    stage3_real[4] <= stage2_real[0] - stage2_real[1];
                    stage3_imag[4] <= stage2_imag[0] - stage2_imag[1];
                    stage3_real[5] <= stage2_real[4] - mult_out_real[0];
                    stage3_imag[5] <= stage2_imag[4] - mult_out_imag[0];
                    stage3_real[6] <= stage2_real[2] - mult_out_real[1];
                    stage3_imag[6] <= stage2_imag[2] - mult_out_imag[1];
                    stage3_real[7] <= stage2_real[6] - mult_out_real[2];
                    stage3_imag[7] <= stage2_imag[6] - mult_out_imag[2];
                end
                
                3'd4: begin
                    pipeline_stage <= 0;
                    processing <= 0;
                    valid <= 1;
                    // Output with bit-reversal (DIT FFT characteristic)
                    X0_real <= stage3_real[0]; X0_imag <= stage3_imag[0]; // 000 -> 000
                    X1_real <= stage3_real[4]; X1_imag <= stage3_imag[4]; // 100 -> 001
                    X2_real <= stage3_real[2]; X2_imag <= stage3_imag[2]; // 010 -> 010
                    X3_real <= stage3_real[6]; X3_imag <= stage3_imag[6]; // 110 -> 011
                    X4_real <= stage3_real[1]; X4_imag <= stage3_imag[1]; // 001 -> 100
                    X5_real <= stage3_real[5]; X5_imag <= stage3_imag[5]; // 101 -> 101
                    X6_real <= stage3_real[3]; X6_imag <= stage3_imag[3]; // 011 -> 110
                    X7_real <= stage3_real[7]; X7_imag <= stage3_imag[7]; // 111 -> 111
                end
                
                default: pipeline_stage <= 0;
            endcase
        end
    end

endmodule

// Complex multiplier module
module complex_mult(
    input clk,
    input signed [31:0] a_real, a_imag,
    input signed [31:0] b_real, b_imag,
    output reg signed [31:0] result_real, result_imag
);

    reg signed [63:0] temp_real, temp_imag;
    reg signed [63:0] ac, bd, ad, bc;

    always @(posedge clk) begin
        // Stage 1: Multiply components
        ac <= a_real * b_real;
        bd <= a_imag * b_imag;
        ad <= a_real * b_imag;
        bc <= a_imag * b_real;
        
        // Stage 2: Combine results
        // (a+jb)(c+jd) = (ac-bd) + j(ad+bc)
        temp_real <= ac - bd;
        temp_imag <= ad + bc;
        
        // Stage 3: Scale back from Q31.32 to Q15.16
        result_real <= temp_real[47:16];  // Keep upper 32 bits
        result_imag <= temp_imag[47:16];  // Keep upper 32 bits
    end

endmodule

fft8_test/fft8_tb.v
`timescale 1ns/1ps

module fft8_tb;
    // Clock and reset
    reg clk, rst, start;
    
    // Input signals (16-bit signed for real and imaginary parts)
    reg signed [15:0] x0_real, x1_real, x2_real, x3_real, x4_real, x5_real, x6_real, x7_real;
    reg signed [15:0] x0_imag, x1_imag, x2_imag, x3_imag, x4_imag, x5_imag, x6_imag, x7_imag;
    
    // Output signals (32-bit signed for real and imaginary parts)
    wire signed [31:0] X0_real, X1_real, X2_real, X3_real, X4_real, X5_real, X6_real, X7_real;
    wire signed [31:0] X0_imag, X1_imag, X2_imag, X3_imag, X4_imag, X5_imag, X6_imag, X7_imag;
    wire valid;

    // Expected results for verification
    reg signed [31:0] expected_real [0:7];
    reg signed [31:0] expected_imag [0:7];
    
    // Error tracking
    integer error_count;
    real tolerance = 1000.0; // Allow some tolerance for fixed-point arithmetic

    // Instantiate the FFT module
    fft8 uut (
        .clk(clk), .rst(rst), .start(start),
        .x0_real(x0_real), .x1_real(x1_real), .x2_real(x2_real), .x3_real(x3_real),
        .x4_real(x4_real), .x5_real(x5_real), .x6_real(x6_real), .x7_real(x7_real),
        .x0_imag(x0_imag), .x1_imag(x1_imag), .x2_imag(x2_imag), .x3_imag(x3_imag),
        .x4_imag(x4_imag), .x5_imag(x5_imag), .x6_imag(x6_imag), .x7_imag(x7_imag),
        .X0_real(X0_real), .X1_real(X1_real), .X2_real(X2_real), .X3_real(X3_real),
        .X4_real(X4_real), .X5_real(X5_real), .X6_real(X6_real), .X7_real(X7_real),
        .X0_imag(X0_imag), .X1_imag(X1_imag), .X2_imag(X2_imag), .X3_imag(X3_imag),
        .X4_imag(X4_imag), .X5_imag(X5_imag), .X6_imag(X6_imag), .X7_imag(X7_imag),
        .valid(valid)
    );

    // Clock generation: 10ns period (100MHz)
    always #5 clk = ~clk;

    // Task to check results
    task check_results;
        input [7*8-1:0] test_name;
        integer i;
        real real_error, imag_error;
        begin
            $display("\n=== %s ===", test_name);
            $display("Index | Expected Real | Expected Imag | Actual Real   | Actual Imag   | Error");
            $display("------|---------------|---------------|---------------|---------------|-------");
            
            error_count = 0;
            for (i = 0; i < 8; i = i + 1) begin
                case (i)
                    0: begin
                        real_error = $abs($signed(expected_real[i]) - $signed(X0_real));
                        imag_error = $abs($signed(expected_imag[i]) - $signed(X0_imag));
                        $display("  %0d   | %11d   | %11d   | %11d   | %11d   | %5.1f", 
                                i, expected_real[i], expected_imag[i], X0_real, X0_imag, real_error + imag_error);
                    end
                    1: begin
                        real_error = $abs($signed(expected_real[i]) - $signed(X1_real));
                        imag_error = $abs($signed(expected_imag[i]) - $signed(X1_imag));
                        $display("  %0d   | %11d   | %11d   | %11d   | %11d   | %5.1f", 
                                i, expected_real[i], expected_imag[i], X1_real, X1_imag, real_error + imag_error);
                    end
                    2: begin
                        real_error = $abs($signed(expected_real[i]) - $signed(X2_real));
                        imag_error = $abs($signed(expected_imag[i]) - $signed(X2_imag));
                        $display("  %0d   | %11d   | %11d   | %11d   | %11d   | %5.1f", 
                                i, expected_real[i], expected_imag[i], X2_real, X2_imag, real_error + imag_error);
                    end
                    3: begin
                        real_error = $abs($signed(expected_real[i]) - $signed(X3_real));
                        imag_error = $abs($signed(expected_imag[i]) - $signed(X3_imag));
                        $display("  %0d   | %11d   | %11d   | %11d   | %11d   | %5.1f", 
                                i, expected_real[i], expected_imag[i], X3_real, X3_imag, real_error + imag_error);
                    end
                    4: begin
                        real_error = $abs($signed(expected_real[i]) - $signed(X4_real));
                        imag_error = $abs($signed(expected_imag[i]) - $signed(X4_imag));
                        $display("  %0d   | %11d   | %11d   | %11d   | %11d   | %5.1f", 
                                i, expected_real[i], expected_imag[i], X4_real, X4_imag, real_error + imag_error);
                    end
                    5: begin
                        real_error = $abs($signed(expected_real[i]) - $signed(X5_real));
                        imag_error = $abs($signed(expected_imag[i]) - $signed(X5_imag));
                        $display("  %0d   | %11d   | %11d   | %11d   | %11d   | %5.1f", 
                                i, expected_real[i], expected_imag[i], X5_real, X5_imag, real_error + imag_error);
                    end
                    6: begin
                        real_error = $abs($signed(expected_real[i]) - $signed(X6_real));
                        imag_error = $abs($signed(expected_imag[i]) - $signed(X6_imag));
                        $display("  %0d   | %11d   | %11d   | %11d   | %11d   | %5.1f", 
                                i, expected_real[i], expected_imag[i], X6_real, X6_imag, real_error + imag_error);
                    end
                    7: begin
                        real_error = $abs($signed(expected_real[i]) - $signed(X7_real));
                        imag_error = $abs($signed(expected_imag[i]) - $signed(X7_imag));
                        $display("  %0d   | %11d   | %11d   | %11d   | %11d   | %5.1f", 
                                i, expected_real[i], expected_imag[i], X7_real, X7_imag, real_error + imag_error);
                    end
                endcase
                
                if ((real_error > tolerance) || (imag_error > tolerance)) begin
                    error_count = error_count + 1;
                    $display("ERROR: Output X[%0d] exceeds tolerance!", i);
                end
            end
            
            if (error_count == 0) begin
                $display("✓ PASS: All outputs within tolerance");
            end else begin
                $display("✗ FAIL: %0d outputs exceed tolerance", error_count);
            end
        end
    endtask

    initial begin
        // Set up waveform dump for GTKWave
        $dumpfile("test.vcd");
        $dumpvars(0, fft8_tb);

        // Initialize signals
        clk = 0;
        rst = 1;
        start = 0;
        error_count = 0;

        // Reset all inputs
        x0_real = 0; x1_real = 0; x2_real = 0; x3_real = 0;
        x4_real = 0; x5_real = 0; x6_real = 0; x7_real = 0;
        x0_imag = 0; x1_imag = 0; x2_imag = 0; x3_imag = 0;
        x4_imag = 0; x5_imag = 0; x6_imag = 0; x7_imag = 0;

        // Hold reset for a few cycles
        #50;
        rst = 0;
        #20;

        // Test Case 1: Real input sequence [1, 2, 3, 4, 5, 6, 7, 8]
        $display("Starting Test Case 1: Real input [1, 2, 3, 4, 5, 6, 7, 8]");
        x0_real = 16'd1; x1_real = 16'd2; x2_real = 16'd3; x3_real = 16'd4;
        x4_real = 16'd5; x5_real = 16'd6; x6_real = 16'd7; x7_real = 16'd8;
        x0_imag = 0; x1_imag = 0; x2_imag = 0; x3_imag = 0;
        x4_imag = 0; x5_imag = 0; x6_imag = 0; x7_imag = 0;
        
        // Expected results (converted to fixed-point Q16.16)
        expected_real[0] = 32'd2359296;   // 36.0 * 65536
        expected_real[1] = -32'd262144;   // -4.0 * 65536
        expected_real[2] = -32'd262144;   // -4.0 * 65536
        expected_real[3] = -32'd262144;   // -4.0 * 65536
        expected_real[4] = -32'd262144;   // -4.0 * 65536
        expected_real[5] = -32'd262144;   // -4.0 * 65536
        expected_real[6] = -32'd262144;   // -4.0 * 65536
        expected_real[7] = -32'd262144;   // -4.0 * 65536
        
        expected_imag[0] = 32'd0;         // 0.0 * 65536
        expected_imag[1] = 32'd632736;    // 9.657 * 65536
        expected_imag[2] = 32'd262144;    // 4.0 * 65536
        expected_imag[3] = 32'd108543;    // 1.657 * 65536
        expected_imag[4] = 32'd0;         // 0.0 * 65536
        expected_imag[5] = -32'd108543;   // -1.657 * 65536
        expected_imag[6] = -32'd262144;   // -4.0 * 65536
        expected_imag[7] = -32'd632736;   // -9.657 * 65536

        start = 1;
        #10;
        start = 0;
        
        // Wait for valid output
        wait(valid);
        #10;
        check_results("Test Case 1");

        #100;

        // Test Case 2: Complex input sequence
        $display("\nStarting Test Case 2: Complex input");
        x0_real = 16'd1; x1_real = 16'd0; x2_real = -16'd1; x3_real = 16'd0;
        x4_real = 16'd1; x5_real = 16'd0; x6_real = -16'd1; x7_real = 16'd0;
        x0_imag = 16'd0; x1_imag = 16'd1; x2_imag = 16'd0; x3_imag = -16'd1;
        x4_imag = 16'd0; x5_imag = 16'd1; x6_imag = 16'd0; x7_imag = -16'd1;
        
        // Expected results for this complex test case
        expected_real[0] = 32'd0;         // 0.0 * 65536
        expected_real[1] = 32'd0;         // 0.0 * 65536
        expected_real[2] = 32'd262144;    // 4.0 * 65536
        expected_real[3] = 32'd0;         // 0.0 * 65536
        expected_real[4] = 32'd0;         // 0.0 * 65536
        expected_real[5] = 32'd0;         // 0.0 * 65536
        expected_real[6] = 32'd262144;    // 4.0 * 65536
        expected_real[7] = 32'd0;         // 0.0 * 65536
        
        expected_imag[0] = 32'd0;         // 0.0 * 65536
        expected_imag[1] = 32'd262144;    // 4.0 * 65536
        expected_imag[2] = 32'd0;         // 0.0 * 65536
        expected_imag[3] = 32'd262144;    // 4.0 * 65536
        expected_imag[4] = 32'd0;         // 0.0 * 65536
        expected_imag[5] = 32'd262144;    // 4.0 * 65536
        expected_imag[6] = 32'd0;         // 0.0 * 65536
        expected_imag[7] = 32'd262144;    // 4.0 * 65536

        start = 1;
        #10;
        start = 0;
        
        wait(valid);
        #10;
        check_results("Test Case 2");

        #100;

        // Test Case 3: All zeros (edge case)
        $display("\nStarting Test Case 3: All zeros");
        x0_real = 0; x1_real = 0; x2_real = 0; x3_real = 0;
        x4_real = 0; x5_real = 0; x6_real = 0; x7_real = 0;
        x0_imag = 0; x1_imag = 0; x2_imag = 0; x3_imag = 0;
        x4_imag = 0; x5_imag = 0; x6_imag = 0; x7_imag = 0;
        
        // Expected: all zeros
        for (integer j = 0; j < 8; j = j + 1) begin
            expected_real[j] = 0;
            expected_imag[j] = 0;
        end

        start = 1;
        #10;
        start = 0;
        
        wait(valid);
        #10;
        check_results("Test Case 3");

        #100;

        // Summary
        $display("\n=== SIMULATION SUMMARY ===");
        $display("FFT module verification completed");
        $display("All test cases processed");
        $display("Note: Small errors are expected due to fixed-point arithmetic");
        
        $finish;
    end

endmodule

fft8_test/test.vcd
$date
	Sun Jul 06 17:44:18 2025
$end
$version
	Icarus Verilog
$end
$timescale
	1ps
$end
$scope module fft8_tb $end
$var wire 1 ! valid $end
$var wire 32 " X7_real [31:0] $end
$var wire 32 # X7_imag [31:0] $end
$var wire 32 $ X6_real [31:0] $end
$var wire 32 % X6_imag [31:0] $end
$var wire 32 & X5_real [31:0] $end
$var wire 32 ' X5_imag [31:0] $end
$var wire 32 ( X4_real [31:0] $end
$var wire 32 ) X4_imag [31:0] $end
$var wire 32 * X3_real [31:0] $end
$var wire 32 + X3_imag [31:0] $end
$var wire 32 , X2_real [31:0] $end
$var wire 32 - X2_imag [31:0] $end
$var wire 32 . X1_real [31:0] $end
$var wire 32 / X1_imag [31:0] $end
$var wire 32 0 X0_real [31:0] $end
$var wire 32 1 X0_imag [31:0] $end
$var reg 1 2 clk $end
$var reg 1 3 rst $end
$var reg 1 4 start $end
$var reg 16 5 x0_imag [15:0] $end
$var reg 16 6 x0_real [15:0] $end
$var reg 16 7 x1_imag [15:0] $end
$var reg 16 8 x1_real [15:0] $end
$var reg 16 9 x2_imag [15:0] $end
$var reg 16 : x2_real [15:0] $end
$var reg 16 ; x3_imag [15:0] $end
$var reg 16 < x3_real [15:0] $end
$var reg 16 = x4_imag [15:0] $end
$var reg 16 > x4_real [15:0] $end
$var reg 16 ? x5_imag [15:0] $end
$var reg 16 @ x5_real [15:0] $end
$var reg 16 A x6_imag [15:0] $end
$var reg 16 B x6_real [15:0] $end
$var reg 16 C x7_imag [15:0] $end
$var reg 16 D x7_real [15:0] $end
$var integer 32 E error_count [31:0] $end
$var real 1 F tolerance $end
$scope module uut $end
$var wire 1 2 clk $end
$var wire 1 3 rst $end
$var wire 1 4 start $end
$var wire 16 G x0_imag [15:0] $end
$var wire 16 H x0_real [15:0] $end
$var wire 16 I x1_imag [15:0] $end
$var wire 16 J x1_real [15:0] $end
$var wire 16 K x2_imag [15:0] $end
$var wire 16 L x2_real [15:0] $end
$var wire 16 M x3_imag [15:0] $end
$var wire 16 N x3_real [15:0] $end
$var wire 16 O x4_imag [15:0] $end
$var wire 16 P x4_real [15:0] $end
$var wire 16 Q x5_imag [15:0] $end
$var wire 16 R x5_real [15:0] $end
$var wire 16 S x6_imag [15:0] $end
$var wire 16 T x6_real [15:0] $end
$var wire 16 U x7_imag [15:0] $end
$var wire 16 V x7_real [15:0] $end
$var parameter 16 W TW_1_IMAG $end
$var parameter 16 X TW_1_REAL $end
$var parameter 16 Y TW_2_IMAG $end
$var parameter 16 Z TW_2_REAL $end
$var parameter 16 [ TW_3_IMAG $end
$var parameter 16 \ TW_3_REAL $end
$var reg 32 ] X0_imag [31:0] $end
$var reg 32 ^ X0_real [31:0] $end
$var reg 32 _ X1_imag [31:0] $end
$var reg 32 ` X1_real [31:0] $end
$var reg 32 a X2_imag [31:0] $end
$var reg 32 b X2_real [31:0] $end
$var reg 32 c X3_imag [31:0] $end
$var reg 32 d X3_real [31:0] $end
$var reg 32 e X4_imag [31:0] $end
$var reg 32 f X4_real [31:0] $end
$var reg 32 g X5_imag [31:0] $end
$var reg 32 h X5_real [31:0] $end
$var reg 32 i X6_imag [31:0] $end
$var reg 32 j X6_real [31:0] $end
$var reg 32 k X7_imag [31:0] $end
$var reg 32 l X7_real [31:0] $end
$var reg 3 m pipeline_stage [2:0] $end
$var reg 1 n processing $end
$var reg 1 ! valid $end
$scope module cmult0 $end
$var wire 32 o a_imag [31:0] $end
$var wire 32 p a_real [31:0] $end
$var wire 32 q b_imag [31:0] $end
$var wire 32 r b_real [31:0] $end
$var wire 1 2 clk $end
$var reg 64 s ac [63:0] $end
$var reg 64 t ad [63:0] $end
$var reg 64 u bc [63:0] $end
$var reg 64 v bd [63:0] $end
$var reg 32 w result_imag [31:0] $end
$var reg 32 x result_real [31:0] $end
$var reg 64 y temp_imag [63:0] $end
$var reg 64 z temp_real [63:0] $end
$upscope $end
$scope module cmult1 $end
$var wire 32 { a_imag [31:0] $end
$var wire 32 | a_real [31:0] $end
$var wire 32 } b_imag [31:0] $end
$var wire 32 ~ b_real [31:0] $end
$var wire 1 2 clk $end
$var reg 64 !" ac [63:0] $end
$var reg 64 "" ad [63:0] $end
$var reg 64 #" bc [63:0] $end
$var reg 64 $" bd [63:0] $end
$var reg 32 %" result_imag [31:0] $end
$var reg 32 &" result_real [31:0] $end
$var reg 64 '" temp_imag [63:0] $end
$var reg 64 (" temp_real [63:0] $end
$upscope $end
$scope module cmult2 $end
$var wire 32 )" a_imag [31:0] $end
$var wire 32 *" a_real [31:0] $end
$var wire 32 +" b_imag [31:0] $end
$var wire 32 ," b_real [31:0] $end
$var wire 1 2 clk $end
$var reg 64 -" ac [63:0] $end
$var reg 64 ." ad [63:0] $end
$var reg 64 /" bc [63:0] $end
$var reg 64 0" bd [63:0] $end
$var reg 32 1" result_imag [31:0] $end
$var reg 32 2" result_real [31:0] $end
$var reg 64 3" temp_imag [63:0] $end
$var reg 64 4" temp_real [63:0] $end
$upscope $end
$scope module cmult3 $end
$var wire 32 5" a_imag [31:0] $end
$var wire 32 6" a_real [31:0] $end
$var wire 32 7" b_imag [31:0] $end
$var wire 32 8" b_real [31:0] $end
$var wire 1 2 clk $end
$var reg 64 9" ac [63:0] $end
$var reg 64 :" ad [63:0] $end
$var reg 64 ;" bc [63:0] $end
$var reg 64 <" bd [63:0] $end
$var reg 32 =" result_imag [31:0] $end
$var reg 32 >" result_real [31:0] $end
$var reg 64 ?" temp_imag [63:0] $end
$var reg 64 @" temp_real [63:0] $end
$upscope $end
$upscope $end
$scope begin $ivl_for_loop0 $end
$var integer 32 A" j [31:0] $end
$upscope $end
$scope task check_results $end
$var reg 56 B" test_name [55:0] $end
$var integer 32 C" i [31:0] $end
$var real 1 D" imag_error $end
$var real 1 E" real_error $end
$upscope $end
$upscope $end
$enddefinitions $end
$comment Show the parameter values. $end
$dumpall
b1010010101111110 \
b1010010101111110 [
b0 Z
b1000000000000000 Y
b101101010000010 X
b1010010101111110 W
$end
#0
$dumpvars
r0 E"
r0 D"
bx C"
bx B"
bx A"
bx @"
bx ?"
bx >"
bx ="
bx <"
bx ;"
bx :"
bx 9"
b10100101011111100000000000000000 8"
b10100101011111100000000000000000 7"
bx 6"
bx 5"
bx 4"
bx 3"
bx 2"
bx 1"
bx 0"
bx /"
bx ."
bx -"
b1011010100000100000000000000000 ,"
b10100101011111100000000000000000 +"
bx *"
bx )"
bx ("
bx '"
bx &"
bx %"
bx $"
bx #"
bx ""
bx !"
b0 ~
b10000000000000000000000000000000 }
bx |
bx {
bx z
bx y
bx x
bx w
bx v
bx u
bx t
bx s
b1011010100000100000000000000000 r
b10100101011111100000000000000000 q
bx p
bx o
0n
b0 m
b0 l
b0 k
b0 j
b0 i
b0 h
b0 g
b0 f
b0 e
b0 d
b0 c
b0 b
b0 a
b0 `
b0 _
b0 ^
b0 ]
b0 V
b0 U
b0 T
b0 S
b0 R
b0 Q
b0 P
b0 O
b0 N
b0 M
b0 L
b0 K
b0 J
b0 I
b0 H
b0 G
r1000 F
b0 E
b0 D
b0 C
b0 B
b0 A
b0 @
b0 ?
b0 >
b0 =
b0 <
b0 ;
b0 :
b0 9
b0 8
b0 7
b0 6
b0 5
04
13
02
b0 1
b0 0
b0 /
b0 .
b0 -
b0 ,
b0 +
b0 *
b0 )
b0 (
b0 '
b0 &
b0 %
b0 $
b0 #
b0 "
0!
$end
#5000
12
#10000
02
#15000
12
#20000
02
#25000
12
#30000
02
#35000
12
#40000
02
#45000
12
#50000
02
03
#55000
12
#60000
02
#65000
12
#70000
02
14
b1000 D
b1000 V
b111 B
b111 T
b110 @
b110 R
b101 >
b101 P
b100 <
b100 N
b11 :
b11 L
b10 8
b10 J
b1 6
b1 H
#75000
b1 m
1n
12
#80000
02
04
#85000
b0 5"
b0 6"
b0 )"
b11111111111110000000000000000000 *"
b0 {
b11111111111111000000000000000000 |
b0 o
b101000000000000000000 p
b10 m
12
#90000
02
#95000
b0 ;"
b0 :"
b0 <"
b0 9"
b0 /"
b10110101000001000000000000000000000000000000000000 ."
b0 0"
b1111111111111101001010111111000000000000000000000000000000000000 -"
b0 #"
b10000000000000000000000000000000000000000000000000 ""
b0 $"
b0 !"
b0 u
b1111111111111000111011011101100000000000000000000000000000000000 t
b0 v
b111000100100010100000000000000000000000000000000000 s
b11 m
12
#100000
02
#105000
b1111111111111000111011011101100000000000000000000000000000000000 y
b111000100100010100000000000000000000000000000000000 z
b10000000000000000000000000000000000000000000000000 '"
b0 ("
b10110101000001000000000000000000000000000000000000 3"
b1111111111111101001010111111000000000000000000000000000000000000 4"
b0 ?"
b0 @"
b100 m
12
#110000
02
#115000
b0 ="
b0 >"
b11010100000100000000000000000000 1"
b101011111100000000000000000000 2"
b0 %"
b0 &"
b11101101110110000000000000000000 w
b10010001010000000000000000000 x
bx #
bx k
bx "
bx l
bx %
bx i
bx $
bx j
bx '
bx g
bx &
bx h
bx )
bx e
bx (
bx f
bx +
bx c
bx *
bx d
bx -
bx a
bx ,
bx b
b11111111111111000000000000000000 .
b11111111111111000000000000000000 `
b1001000000000000000000 0
b1001000000000000000000 ^
1!
0n
b0 m
12
#120000
02
#125000
0!
12
b1 E
r0 D"
b1000 C"
b100000010000110110000101110011011001010010000000110001 B"
#130000
02
#135000
12
#140000
02
#145000
12
#150000
02
#155000
12
#160000
02
#165000
12
#170000
02
#175000
12
#180000
02
#185000
12
#190000
02
#195000
12
#200000
02
#205000
12
#210000
02
#215000
12
#220000
02
#225000
b1 m
1n
12
14
b1111111111111111 C
b1111111111111111 U
b1 ?
b1 Q
b1111111111111111 ;
b1111111111111111 M
b1 7
b1 I
b0 D
b0 V
b1111111111111111 B
b1111111111111111 T
b0 @
b0 R
b1 >
b1 P
b0 <
b0 N
b1111111111111111 :
b1111111111111111 L
b0 8
b0 J
#230000
02
#235000
b0 *"
b1000000000000000000 {
b0 |
b0 p
b10 m
12
04
#240000
02
#245000
b0 t
b0 s
b0 ""
b1111111111111110000000000000000000000000000000000000000000000000 $"
b0 ."
b0 -"
b11 m
12
#250000
02
#255000
b0 3"
b0 4"
b0 '"
b10000000000000000000000000000000000000000000000000 ("
b0 y
b0 z
b100 m
12
#260000
02
#265000
b0 w
b0 x
b0 1"
b0 2"
b101011111100000000000000000000 #
b101011111100000000000000000000 k
b11010100000100000000000000000000 "
b11010100000100000000000000000000 l
b11010100000100000000000000000000 %
b11010100000100000000000000000000 i
b101011111100000000000000000000 $
b101011111100000000000000000000 j
b10010001010000000000000000000 '
b10010001010000000000000000000 g
b11101101110110000000000000000000 &
b11101101110110000000000000000000 h
b11101101110110000000000000000000 )
b11101101110110000000000000000000 e
b10010001010000000000000000000 (
b10010001010000000000000000000 f
b0 +
b0 c
b1000000000000000000 *
b1000000000000000000 d
b0 -
b0 a
b1000000000000000000 ,
b1000000000000000000 b
b0 .
b0 `
b0 0
b0 ^
1!
0n
b0 m
12
#270000
02
#275000
0!
12
r737148928 E"
r3558080512 D"
b1000 C"
b110 E
b100000010000110110000101110011011001010010000000110010 B"
#280000
02
#285000
12
#290000
02
#295000
12
#300000
02
#305000
12
#310000
02
#315000
12
#320000
02
#325000
12
#330000
02
#335000
12
#340000
02
#345000
12
#350000
02
#355000
12
#360000
02
#365000
12
#370000
02
#375000
b1 m
1n
12
14
b1000 A"
b0 C
b0 U
b0 ?
b0 Q
b0 ;
b0 M
b0 7
b0 I
b0 B
b0 T
b0 >
b0 P
b0 :
b0 L
b0 6
b0 H
#380000
02
